instance_builder/__init__.py
instance_builder/builder.py
instance_builder/getter.py
instance_builder/lib.py
instance_builder/setter.py
instance_builder-0.1.8.dist-info/LICENSE
instance_builder-0.1.8.dist-info/WHEEL
instance_builder-0.1.8.dist-info/METADATA
instance_builder-0.1.8.dist-info/RECORD
