Metadata-Version: 2.1
Name: instance-builder
Version: 0.1.8
Summary: Instance builder library for Python inspired by Lombok
Home-page: https://github.com/shimech/instance-builder
License: MIT
Keywords: Instance Builder,Builder,Lombok
Author: Shuntaro Shimizu
Author-email: ut.s.shimizu@gmail.com
Requires-Python: >=3.9,<4.0
Classifier: License :: OSI Approved :: MIT License
Classifier: Operating System :: OS Independent
Classifier: Programming Language :: Python :: 3
Classifier: Programming Language :: Python :: 3.9
Project-URL: Repository, https://github.com/shimech/instance-builder
